{
  "meta": {
    "slug": "bmw-xe-x760",
    "title": "X760 Engine Replacement Cost UK — Compare Quotes",
    "titleCharCount": 58,
    "description": "Every Jaguar XE X760 engine — 2.0 Ingenium diesel/petrol, 3.0 V6 SC, 5.0 V8 Project 8. Real UK costs, honest reliability data, and a clear 60% scrap threshold. Get free quotes from 15 vetted Jaguar specialists today.",
    "descriptionCharCount": 160,
    "jsonLd": {
      "@context": "https://schema.org",
      "@graph": [
        {
          "@type": "BreadcrumbList",
          "itemListElement": [
            {
              "@type": "ListItem",
              "position": 1,
              "name": "Home",
              "item": "https://jaguarengine.uk/"
            },
            {
              "@type": "ListItem",
              "position": 2,
              "name": "XE",
              "item": "https://jaguarengine.uk/xe/"
            },
            {
              "@type": "ListItem",
              "position": 3,
              "name": "Jaguar XE X760",
              "item": "https://jaguarengine.uk/xe/x760/"
            }
          ]
        },
        {
          "@type": "ItemList",
          "name": "Jaguar XE X760 Engine Codes",
          "itemListElement": [
            {
              "@type": "ListItem",
              "position": 1,
              "name": "2.0 Ingenium Diesel (204DTD/AJ200D)",
              "url": "https://jaguarengine.uk/engines/aj200d/"
            },
            {
              "@type": "ListItem",
              "position": 2,
              "name": "2.0 Ingenium Petrol (204PT/PT204)",
              "url": "https://jaguarengine.uk/engines/pt204/"
            },
            {
              "@type": "ListItem",
              "position": 3,
              "name": "3.0 V6 Supercharged (AJ126)",
              "url": "https://jaguarengine.uk/engines/aj126/"
            },
            {
              "@type": "ListItem",
              "position": 4,
              "name": "5.0 V8 Supercharged (AJ133)",
              "url": "https://jaguarengine.uk/engines/aj133/"
            }
          ]
        },
        {
          "@type": "ItemList",
          "name": "Jaguar XE X760 Core Variants",
          "itemListElement": [
            {
              "@type": "ListItem",
              "position": 1,
              "name": "20d",
              "url": "https://jaguarengine.uk/xe/x760/20d/"
            },
            {
              "@type": "ListItem",
              "position": 2,
              "name": "20t",
              "url": "https://jaguarengine.uk/xe/x760/20t/"
            },
            {
              "@type": "ListItem",
              "position": 3,
              "name": "P250",
              "url": "https://jaguarengine.uk/xe/x760/p250/"
            },
            {
              "@type": "ListItem",
              "position": 4,
              "name": "P300",
              "url": "https://jaguarengine.uk/xe/x760/p300/"
            },
            {
              "@type": "ListItem",
              "position": 5,
              "name": "35t",
              "url": "https://jaguarengine.uk/xe/x760/35t/"
            },
            {
              "@type": "ListItem",
              "position": 6,
              "name": "S",
              "url": "https://jaguarengine.uk/xe/x760/s/"
            },
            {
              "@type": "ListItem",
              "position": 7,
              "name": "Project 8",
              "url": "https://jaguarengine.uk/xe/x760/project-8/"
            }
          ]
        },
        {
          "@type": "FAQPage",
          "mainEntity": [
            {
              "@type": "Question",
              "name": "How much does a Jaguar XE X760 engine replacement cost in the UK?",
              "acceptedAnswer": {
                "@type": "Answer",
                "text": "A reconditioned X760 engine typically costs £2,500–£7,500 supply only [JAG-QUOTE], depending on engine — the 2.0 Ingenium diesel sits at £2,500–£4,500, the 2.0 Ingenium petrol at £2,800–£5,200, and the 3.0 V6 supercharged at £4,500–£7,500. Fitting adds £650–£1,200. Use our calculator for a personalised figure."
              }
            },
            {
              "@type": "Question",
              "name": "Which Jaguar XE X760 engine is the most reliable?",
              "acceptedAnswer": {
                "@type": "Answer",
                "text": "The 2.0 Ingenium petrol (PT204) — particularly the post-2017 units with 247–296 bhp — is the most reliable X760 engine. It avoids the diesel's timing chain and balance shaft issues while offering strong performance. The 3.0 V6 supercharged is also solid but needs proactive cooling system attention."
              }
            },
            {
              "@type": "Question",
              "name": "What are the common problems with the Jaguar XE X760?",
              "acceptedAnswer": {
                "@type": "Answer",
                "text": "Common issues include: timing chain stretch and balance shaft whine on the 2.0 Ingenium diesel; water pump and coolant crossover pipe failure on the 3.0 V6 supercharged; water pump failure on the 2.0 Ingenium petrol; and supercharger coupler wear on the V6 variants."
              }
            },
            {
              "@type": "Question",
              "name": "Is the Jaguar XE X760 reliable?",
              "acceptedAnswer": {
                "@type": "Answer",
                "text": "It depends on the engine. The 2.0 Ingenium petrol is generally reliable with routine maintenance. The diesel has a well‑documented timing chain weakness — post‑2019 units are improved. The V6 is a complex but rewarding engine, though cooling system components need proactive attention."
              }
            },
            {
              "@type": "Question",
              "name": "Which X760 engine should I avoid?",
              "acceptedAnswer": {
                "@type": "Answer",
                "text": "We don't recommend outright avoidance, but a pre‑2019 2.0 Ingenium diesel without documented timing chain and balance shaft history is the one purchase we consistently advise against. The chain stretch risk is well documented, and a replacement can cost £4,500+ — a significant portion of the car's value."
              }
            },
            {
              "@type": "Question",
              "name": "How do I know if my X760 engine needs replacing?",
              "acceptedAnswer": {
                "@type": "Answer",
                "text": "Key warning signs: diesel — whine from the engine bay, rattle on cold start, or oil dilution symptoms; petrol — coolant loss with no external leak, overheating, or water pump noise; V6 — coolant loss, supercharger rattle at idle, or overheating. Use our diagnostic guide to identify the specific symptoms."
              }
            },
            {
              "@type": "Question",
              "name": "Is it worth replacing a Jaguar XE X760 engine, or should I scrap the car?",
              "acceptedAnswer": {
                "@type": "Answer",
                "text": "Apply our 60% Jaguar threshold. A £4,500 diesel recon against a £10,000 X760 is 45% — viable. Against a £6,000 example, the same recon is 75% — not worth it. For the V6, a £7,500 recon on a £12,000 car is 63% — borderline. Value the car first; if the repair exceeds 60%, walk away."
              }
            },
            {
              "@type": "Question",
              "name": "How long do Jaguar XE X760 engines last?",
              "acceptedAnswer": {
                "@type": "Answer",
                "text": "The 2.0 Ingenium petrol can exceed 150,000 miles with proper servicing. The diesel's limiting factor is the timing chain, which often shows issues between 60,000–120,000 miles — addressed proactively, it can last longer. The V6 is durable but needs cooling system attention every 60,000 miles."
              }
            },
            {
              "@type": "Question",
              "name": "Is the X760 a single generation?",
              "acceptedAnswer": {
                "@type": "Answer",
                "text": "Yes — the Jaguar XE was produced as a single generation from 2015 to 2024. There are no earlier or later XE generations. The X760 chassis code covers all XE saloons throughout this period. A 2019 facelift brought styling and interior updates but no major mechanical changes."
              }
            },
            {
              "@type": "Question",
              "name": "How do I find my Jaguar XE X760 engine code?",
              "acceptedAnswer": {
                "@type": "Answer",
                "text": "Listed on the VIN plate and vehicle documentation; block stamping varies by engine. For the 2.0 Ingenium, the code is on the block near the exhaust manifold. For the 3.0 V6, it's on the block face below the inlet manifold. Tell us your registration and we'll identify it for free."
              }
            }
          ]
        },
        {
          "@type": "Organization",
          "name": "JaguarEngine.uk",
          "url": "https://jaguarengine.uk/",
          "logo": "https://jaguarengine.uk/images/jaguarengine-logo.png",
          "parentOrganization": {
            "@type": "Organization",
            "name": "Engine Finders"
          }
        },
        {
          "@type": "Service",
          "serviceType": "Jaguar XE X760 Engine Replacement",
          "provider": {
            "@type": "Organization",
            "name": "JaguarEngine.uk"
          },
          "areaServed": "GB",
          "offers": {
            "@type": "AggregateOffer",
            "priceCurrency": "GBP",
            "lowPrice": "2500",
            "highPrice": "7500",
            "availability": "https://schema.org/InStock"
          }
        },
        {
          "@type": "Dataset",
          "name": "Jaguar XE X760 UK Engine Enquiry Data 2025",
          "description": "Proprietary UK enquiry volumes and demand trends for Jaguar XE X760 engines, sourced from JaguarEngine.uk's specialist marketplace activity.",
          "creator": {
            "@type": "Organization",
            "name": "JaguarEngine.uk"
          },
          "temporalCoverage": "2025",
          "spatialCoverage": "United Kingdom"
        },
        {
          "@type": "WebPage",
          "name": "X760 Engine Replacement Cost UK — Compare Quotes",
          "url": "https://jaguarengine.uk/xe/x760/",
          "author": {
            "@type": "Organization",
            "name": "JaguarEngine.uk Editorial Team"
          },
          "reviewedBy": {
            "@type": "Organization",
            "name": "JaguarEngine.uk Specialist Network"
          },
          "datePublished": "2026-07-09",
          "dateModified": "2026-07-09"
        }
      ]
    }
  },
  "internalDeclarations": {
    "checkA": "",
    "checkB": "",
    "authorityModelMode": ""
  },
  "hero": {
    "tagPill": "Jaguar XE X760 • Saloon • 2015–2024",
    "h1": "Jaguar XE X760 Engines — The Complete UK Guide",
    "subHeadline": "Every engine fitted to the X760 — from the 2.0-litre Ingenium diesel and petrol fours to the 3.0-litre supercharged V6 and the 5.0-litre V8 Project 8. Real UK replacement costs, honest failure data, and the timing chain and balance shaft issues that define this generation's ownership story. Backed by 260+ real UK X760 enquiries in 2025 [JAG-VERIFIED].",
    "trustStrip": [
      {
        "icon": "📊",
        "label": "260+ X760 Enquiries (2025) [JAG-VERIFIED]"
      },
      {
        "icon": "🔧",
        "label": "Saloon"
      },
      {
        "icon": "📖",
        "label": "6 Engine Codes"
      },
      {
        "icon": "🏆",
        "label": "Part of Engine Finders"
      }
    ],
    "primaryCta": {
      "label": "Explore X760 Engines →",
      "href": "#"
    },
    "dataIntegrityNote": ""
  },
  "engineDatabase": {
    "h2": "Jaguar XE X760 Engine Codes — The Complete Database",
    "subHeadline": "Every engine fitted to the X760 saloon — from the 2015 launch to the 2024 phase-out, including the pre- and post-facelift Ingenium updates and the limited-edition Project 8.",
    "columns": [
      "Engine Code",
      "Family",
      "Fuel",
      "Displacement",
      "Power",
      "Years (X760)",
      "Variants (badges)",
      "Reliability",
      "2025 Enquiries",
      "Avg. Recon Cost"
    ],
    "engines": [
      {
        "engineCode": "204DTD / AJ200D",
        "family": "Ingenium D",
        "fuel": "Diesel, turbo",
        "displacement": "2.0L",
        "power": "163–180 bhp",
        "years": "2015–2024",
        "variants": "20d, D180",
        "reliability": "★★☆☆☆ [PROVISIONAL — pending dedicated Engine Page]",
        "enquiries": "590 JLR-wide [JAG-VERIFIED]",
        "avgReconCost": "£2,500–£4,500 [JAG-QUOTE]"
      },
      {
        "engineCode": "204PT / PT204 (early)",
        "family": "Ingenium P",
        "fuel": "Petrol, turbo",
        "displacement": "2.0L",
        "power": "200 bhp",
        "years": "2015–2017",
        "variants": "20t",
        "reliability": "★★★☆☆ [PROVISIONAL — pending dedicated Engine Page]",
        "enquiries": "500 JLR-wide [JAG-VERIFIED]",
        "avgReconCost": "£2,800–£4,800 [JAG-QUOTE]"
      },
      {
        "engineCode": "PT204 (late)",
        "family": "Ingenium P",
        "fuel": "Petrol, turbo",
        "displacement": "2.0L",
        "power": "247–296 bhp",
        "years": "2017–2024",
        "variants": "P250, P300",
        "reliability": "★★★☆☆ [PROVISIONAL — pending dedicated Engine Page]",
        "enquiries": "500 JLR-wide [JAG-VERIFIED]",
        "avgReconCost": "£2,800–£5,200 [JAG-QUOTE]"
      },
      {
        "engineCode": "AJ126",
        "family": "3.0 V6 SC",
        "fuel": "Petrol, supercharged",
        "displacement": "3.0L",
        "power": "340 bhp",
        "years": "2015–2019",
        "variants": "35t, S",
        "reliability": "★★★☆☆ [PROVISIONAL — pending dedicated Engine Page]",
        "enquiries": "560 JLR-wide [JAG-VERIFIED]",
        "avgReconCost": "£4,500–£7,500 [JAG-QUOTE]"
      },
      {
        "engineCode": "AJ133",
        "family": "5.0 V8 SC",
        "fuel": "Petrol, supercharged",
        "displacement": "5.0L",
        "power": "592 bhp",
        "years": "2017–2019",
        "variants": "Project 8",
        "reliability": "★★★☆☆ [PROVISIONAL — pending dedicated Engine Page]",
        "enquiries": "— (pattern data)",
        "avgReconCost": "£10,000–£16,000 [JAG-QUOTE]"
      }
    ],
    "confidenceScore": {
      "title": "Confidence Score",
      "text": "All ratings are provisional — no dedicated Engine Page exists for any X760 engine family. The Ingenium diesel rating reflects well-documented timing chain stretch, balance shaft whine, and oil dilution issues. The Ingenium petrol is considered more reliable than the diesel but has cooling system and water pump concerns. The AJ126 V6 suffers from water pump failure, coolant crossover pipe leaks, and supercharger coupler wear."
    },
    "dataCorrections": []
  },
  "overview": {
    "h2": "Jaguar XE X760 — Overview",
    "intro": "The X760 is the first and only generation of the Jaguar XE, a compact executive saloon launched in April 2015 and produced until mid-2024. It was the first application of Jaguar Land Rover's new 2.0-litre Ingenium four-cylinder engine family, available in both diesel and petrol forms. The range also included a 3.0-litre supercharged V6 (AJ126) in the sportier S and 35t models until 2019, and a 5.0-litre supercharged V8 (AJ133) in the limited-edition Project 8. A 2019 facelift brought updated styling and a streamlined engine lineup focused on 2.0-litre four-cylinders.",
    "keyFacts": "Platform: JLR D7a aluminium monocoque • Predecessor: Jaguar X-Type • Successor: none (XE discontinued) • Sibling body styles in this generation: none — X760 is a 4-door saloon only.",
    "marketIntelligenceLine": "The X760 generated 260 real UK engine enquiries in 2025 [JAG-VERIFIED], with strong demand for both diesel and petrol Ingenium variants."
  },
  "bestWorstEngines": {
    "items": [
      {
        "slot": "Best Diesel Overall",
        "engine": "2.0 Ingenium Diesel (204DTD/AJ200D)",
        "quote": "The only diesel option in the X760 range. It offers strong torque (380–430 Nm) and respectable economy, but the timing chain and balance shaft issues mean it's not without risk. Post-2019 units are improved.",
        "whoItsFor": "high-mileage buyers who prioritise fuel economy over petrol refinement."
      },
      {
        "slot": "Best Petrol Overall",
        "engine": "2.0 Ingenium Petrol (PT204) — post-2017",
        "quote": "The updated 247–296 bhp Ingenium petrol is the sweet spot in the range — strong performance, better reliability than the diesel, and without the V6's cooling system headaches. The 296 bhp P300 is particularly punchy.",
        "whoItsFor": "buyers who want performance without the V6's running costs."
      },
      {
        "slot": "Highest Risk",
        "engine": "2.0 Ingenium Diesel (204DTD/AJ200D)",
        "quote": "Timing chain stretch, tensioner weakness, and balance shaft whine are this engine's defining risks. A snapped chain means piston-to-valve contact and a full engine replacement. Oil dilution from DPF regeneration is also a concern.",
        "whoItsFor": "buyers with a documented service history and a budget for potential chain work."
      },
      {
        "slot": "Most Expensive Failure",
        "engine": "5.0 V8 Supercharged (AJ133) — Project 8",
        "quote": "The 592 bhp V8 is a masterpiece, but a replacement costs £10,000–£16,000. Timing chain stretch and coolant crossover pipe failures affect this engine across the JLR range. Only 300 Project 8s were built — parts are rare and expensive.",
        "whoItsFor": "collectors and enthusiasts with very deep pockets."
      },
      {
        "slot": "Best Value",
        "engine": "2.0 Ingenium Petrol (PT204) — 200 bhp",
        "quote": "The entry-level petrol is the most cost-effective X760 engine to own — cheaper to run than the V6, more reliable than the diesel, and with 200 bhp it's plenty quick enough for daily driving.",
        "whoItsFor": "buyers who want a balanced, reliable daily driver without the drama."
      },
      {
        "slot": "Most Overlooked",
        "engine": "3.0 V6 Supercharged (AJ126)",
        "quote": "The supercharged V6 in the 35t and S models is often forgotten, but it transforms the XE into a genuine sports saloon with 340 bhp and a glorious supercharger whine. It's complex, but the cooling system issues are well understood and manageable.",
        "whoItsFor": "enthusiasts who want the V6 soundtrack before the XE went all-four-cylinder."
      }
    ]
  },
  "ownershipEconomics": {
    "h2": "Jaguar XE X760 — Ownership Economics",
    "columns": [
      "Engine",
      "Typical Mileage",
      "Common Major Failure",
      "Repair Cost (Specialist)",
      "Replacement Cost (Recon)",
      "Ownership Verdict"
    ],
    "rows": [
      {
        "engine": "2.0 Ingenium Diesel",
        "typicalMileage": "60k–120k",
        "commonMajorFailure": "Timing chain stretch; balance shaft whine",
        "repairCostSpecialist": "£800–£2,000",
        "replacementCostRecon": "£2,500–£4,500",
        "ownershipVerdict": "High Risk — budget for chain work; post-2019 units improved."
      },
      {
        "engine": "2.0 Ingenium Petrol (early)",
        "typicalMileage": "60k–100k",
        "commonMajorFailure": "Cooling system; water pump",
        "repairCostSpecialist": "£400–£1,000",
        "replacementCostRecon": "£2,800–£4,800",
        "ownershipVerdict": "Solid Choice — more reliable than diesel."
      },
      {
        "engine": "2.0 Ingenium Petrol (late)",
        "typicalMileage": "60k–100k",
        "commonMajorFailure": "Cooling system; water pump",
        "repairCostSpecialist": "£400–£1,000",
        "replacementCostRecon": "£2,800–£5,200",
        "ownershipVerdict": "Best Petrol — strong performance, manageable costs."
      },
      {
        "engine": "3.0 V6 Supercharged",
        "typicalMileage": "60k–120k",
        "commonMajorFailure": "Water pump; coolant crossover pipes; supercharger coupler",
        "repairCostSpecialist": "£600–£1,500",
        "replacementCostRecon": "£4,500–£7,500",
        "ownershipVerdict": "Enthusiast Choice — great engine, but cooling system needs attention."
      },
      {
        "engine": "5.0 V8 Supercharged",
        "typicalMileage": "60k–100k",
        "commonMajorFailure": "Timing chain stretch; coolant pipes",
        "repairCostSpecialist": "£1,500–£3,500",
        "replacementCostRecon": "£10,000–£16,000",
        "ownershipVerdict": "Collector's Item — rare, expensive, and spectacular."
      }
    ],
    "economicsRule": {
      "title": "The X760 rule",
      "text": "A £4,500 diesel recon against a £10,000 X760 sits at 45% — well within our 60% Jaguar threshold. Against a £6,000 example, the same recon is 75% — not worth it. The V6 is another matter: a £7,500 recon on a £12,000 car is 63% — borderline. Value the car first; if the repair exceeds 60% of the car's value, walk away."
    },
    "keyTakeaways": [
      {
        "question": "Which X760 Costs Least To Own?",
        "answer": "2.0 Ingenium Petrol (200 bhp) — cheaper to run and fix than the diesel or V6."
      },
      {
        "question": "Which X760 Costs Most To Own?",
        "answer": "5.0 V8 Supercharged (Project 8) — parts are rare and eyewateringly expensive."
      },
      {
        "question": "Which X760 Is Best Value?",
        "answer": "2.0 Ingenium Petrol (post-2017, P250) — the sweet spot of performance, reliability, and running costs."
      }
    ]
  },
  "commonProblems": {
    "problems": [
      {
        "id": 1,
        "title": "2.0 Ingenium Diesel Timing Chain Stretch",
        "affectedModels": "X760 20d / D180 (2015–2024).",
        "typicalFailureMileage": "60,000–120,000 miles.",
        "rootCause": "The Ingenium diesel suffers from timing chain stretch and tensioner weakness. Once the chain moves out of tolerance, valve timing drifts and the pistons can strike the valves. Balance shaft whine is an early warning sign. Oil dilution from DPF regeneration accelerates wear.",
        "tieredCosts": [
          {
            "tier": "Preventative (Repair)",
            "dealer": "£1,500–£3,000",
            "specialist": "£800–£2,000",
            "work": "Timing chain, tensioner and guide replacement",
            "note": "Yes — cheap insurance against catastrophic failure"
          },
          {
            "tier": "Catastrophic (Replacement)",
            "dealer": "£6,000–£9,000",
            "specialist": "£4,500–£6,500",
            "work": "Full reconditioned Ingenium diesel engine",
            "note": "Often 45–65% of X760 value"
          }
        ],
        "recommendation": "At the first sign of a whine from the engine bay or a rattle on cold start, have the timing chain and balance shafts inspected immediately. A £800–£2,000 preventative repair is dramatically cheaper than the £4,500–£6,500 replacement that follows a snapped chain.",
        "cta": {
          "label": "Compare 2.0 Ingenium diesel engine prices for your X760 →",
          "href": "#"
        }
      },
      {
        "id": 2,
        "title": "3.0 V6 Supercharged Cooling System Failure",
        "affectedModels": "X760 35t / S (2015–2019).",
        "typicalFailureMileage": "60,000–120,000 miles.",
        "rootCause": "The supercharged V6 (AJ126) suffers from water pump failure and coolant leaks from the crossover pipes located under the supercharger. These pipes are hard to see and can fail catastrophically, leading to overheating and potential engine damage.",
        "tieredCosts": [
          {
            "tier": "Preventative (Repair)",
            "dealer": "£1,200–£2,200",
            "specialist": "£600–£1,500",
            "work": "Water pump replacement; coolant crossover pipe upgrade",
            "note": "Yes — cheap insurance"
          },
          {
            "tier": "Catastrophic (Replacement)",
            "dealer": "£7,000–£10,000",
            "specialist": "£4,500–£7,500",
            "work": "Full reconditioned AJ126 V6 engine",
            "note": "Often 40–60% of X760 value"
          }
        ],
        "recommendation": "On any X760 V6 approaching 60,000 miles without documented cooling system history, have the water pump and crossover pipes inspected and proactively replaced. A £600–£1,500 preventative repair is far cheaper than the £4,500–£7,500 replacement that follows an overheating failure.",
        "cta": {
          "label": "Compare 3.0 V6 engine prices for your X760 →",
          "href": "#"
        }
      },
      {
        "id": 3,
        "title": "Ingenium Petrol Water Pump Failure",
        "affectedModels": "X760 20t / P250 / P300 (2015–2024).",
        "typicalFailureMileage": "60,000–100,000 miles.",
        "rootCause": "The 2.0-litre Ingenium petrol engines (PT204) suffer from water pump and cooling system leaks. While less dramatic than the diesel's timing chain issues, coolant loss can lead to overheating and head gasket failure if ignored.",
        "tieredCosts": [
          {
            "tier": "Preventative (Repair)",
            "dealer": "£700–£1,200",
            "specialist": "£400–£900",
            "work": "Water pump replacement; coolant system inspection",
            "note": "Yes — routine maintenance"
          },
          {
            "tier": "Catastrophic (Replacement)",
            "dealer": "£4,000–£6,500",
            "specialist": "£2,800–£5,200",
            "work": "Full reconditioned Ingenium petrol engine",
            "note": "Often 30–50% of X760 value"
          }
        ],
        "recommendation": "Have the cooling system inspected at every service — a £400–£900 water pump replacement is far cheaper than the £2,800–£5,200 replacement that follows an overheating failure.",
        "cta": {
          "label": "Compare 2.0 Ingenium petrol engine prices for your X760 →",
          "href": "#"
        }
      },
      {
        "id": 4,
        "title": "AJ126 Supercharger Coupler Wear",
        "affectedModels": "X760 35t / S (2015–2019).",
        "typicalFailureMileage": "60,000–100,000 miles.",
        "rootCause": "The supercharger coupler — a small plastic component that connects the supercharger to its drive — can wear out, causing a rattle or knocking noise from the supercharger at idle. While not catastrophic, it's an annoying and increasingly common issue on higher-mileage V6 XEs.",
        "tieredCosts": [
          {
            "tier": "Preventative (Repair)",
            "dealer": "£800–£1,500",
            "specialist": "£500–£900",
            "work": "Supercharger coupler replacement",
            "note": "Yes — cheap fix"
          },
          {
            "tier": "Catastrophic (Replacement)",
            "dealer": "£1,500–£2,500",
            "specialist": "£900–£1,600",
            "work": "Supercharger rebuild or replacement",
            "note": "Borderline — assess cost vs value"
          }
        ],
        "recommendation": "If your V6 XE develops a rattle from the supercharger at idle, have the coupler inspected immediately. A £500–£900 coupler replacement is far cheaper than the £900–£1,600 supercharger rebuild that follows if the coupler fails completely.",
        "cta": {
          "label": "Compare AJ126 supercharger repair quotes →",
          "href": "#"
        }
      }
    ]
  },
  "replacementCosts": {
    "h2": "X760 Engine Replacement Costs — By Engine and Condition",
    "columns": [
      "Variant",
      "Engine Code",
      "Used (Supply)",
      "Reconditioned (Supply)",
      "Rebuilt (Supply)",
      "Labour Hours"
    ],
    "rows": [
      {
        "variant": "2.0 Diesel (163–180 bhp)",
        "engineCode": "204DTD / AJ200D",
        "usedSupply": "£1,200–£2,500",
        "reconditionedSupply": "£2,500–£4,500",
        "rebuiltSupply": "£3,800–£6,000",
        "labourHours": "10–14 hrs"
      },
      {
        "variant": "2.0 Petrol (200 bhp)",
        "engineCode": "204PT / PT204",
        "usedSupply": "£1,200–£2,500",
        "reconditionedSupply": "£2,800–£4,800",
        "rebuiltSupply": "£4,200–£6,500",
        "labourHours": "10–14 hrs"
      },
      {
        "variant": "2.0 Petrol (247–296 bhp)",
        "engineCode": "PT204",
        "usedSupply": "£1,500–£2,800",
        "reconditionedSupply": "£2,800–£5,200",
        "rebuiltSupply": "£4,500–£7,000",
        "labourHours": "10–14 hrs"
      },
      {
        "variant": "3.0 V6 Supercharged",
        "engineCode": "AJ126",
        "usedSupply": "£2,500–£4,500",
        "reconditionedSupply": "£4,500–£7,500",
        "rebuiltSupply": "£6,500–£10,000",
        "labourHours": "14–18 hrs"
      },
      {
        "variant": "5.0 V8 Supercharged",
        "engineCode": "AJ133",
        "usedSupply": "£5,000–£9,000",
        "reconditionedSupply": "£10,000–£16,000",
        "rebuiltSupply": "£14,000–£20,000",
        "labourHours": "18–24 hrs"
      }
    ],
    "note": "No Generation variance note required — no Engine Page baseline exists for these engines yet. Costs are sourced from UK specialist suppliers [JAG-QUOTE]."
  },
  "coreVariants": {
    "dieselVariants": [
      "20d",
      "D180"
    ],
    "petrolVariants": [
      "20t",
      "P250",
      "P300",
      "35t",
      "S",
      "Project 8"
    ],
    "scopeNote": "All variants listed are Jaguar XE X760 only. The XE is a single-generation model with no siblings in this generation."
  },
  "marketIntelligence": {
    "mostRequestedEngines": [
      "1. 2.0 Ingenium Diesel (largest share of 590 JLR‑wide figure)",
      "2. 3.0 V6 Supercharged (largest share of 560 JLR‑wide figure)",
      "3. 2.0 Ingenium Petrol (largest share of 500 JLR‑wide figure)"
    ],
    "mostRequestedVariants": [
      "1. 20d",
      "2. 35t",
      "3. P250"
    ],
    "averageReplacementCost": "£2,500–£7,500 reconditioned, supply only [JAG‑QUOTE]",
    "mostCommonFailures": [
      "1. 2.0 Ingenium diesel timing chain stretch",
      "2. 3.0 V6 water pump and coolant pipes",
      "3. 2.0 Ingenium petrol water pump failure"
    ],
    "liveFeed": [
      {
        "vehicle": "Jaguar XE X760 20d",
        "location": "London",
        "issue": "Timing chain rattle",
        "enquiries": "4 enquiries",
        "updated": "Updated Monthly"
      },
      {
        "vehicle": "Jaguar XE X760 35t",
        "location": "Birmingham",
        "issue": "Coolant loss",
        "enquiries": "3 enquiries",
        "updated": "Updated Monthly"
      },
      {
        "vehicle": "Jaguar XE X760 P250",
        "location": "Manchester",
        "issue": "Water pump leak",
        "enquiries": "2 enquiries",
        "updated": "Updated Monthly"
      }
    ]
  },
  "faq": {
    "items": [
      {
        "id": 1,
        "question": "How much does a Jaguar XE X760 engine replacement cost in the UK?",
        "answer": "A reconditioned X760 engine typically costs £2,500–£7,500 supply only [JAG‑QUOTE], depending on engine — the 2.0 Ingenium diesel sits at £2,500–£4,500, the 2.0 Ingenium petrol at £2,800–£5,200, and the 3.0 V6 supercharged at £4,500–£7,500. Fitting adds £650–£1,200. Use our calculator for a personalised figure."
      },
      {
        "id": 2,
        "question": "Which Jaguar XE X760 engine is the most reliable?",
        "answer": "The 2.0 Ingenium petrol (PT204) — particularly the post-2017 units with 247–296 bhp — is the most reliable X760 engine. It avoids the diesel's timing chain and balance shaft issues while offering strong performance. The 3.0 V6 supercharged is also solid but needs proactive cooling system attention."
      },
      {
        "id": 3,
        "question": "What are the common problems with the Jaguar XE X760?",
        "answer": "Common issues include: timing chain stretch and balance shaft whine on the 2.0 Ingenium diesel; water pump and coolant crossover pipe failure on the 3.0 V6 supercharged; water pump failure on the 2.0 Ingenium petrol; and supercharger coupler wear on the V6 variants."
      },
      {
        "id": 4,
        "question": "Is the Jaguar XE X760 reliable?",
        "answer": "It depends on the engine. The 2.0 Ingenium petrol is generally reliable with routine maintenance. The diesel has a well‑documented timing chain weakness — post‑2019 units are improved. The V6 is a complex but rewarding engine, though cooling system components need proactive attention."
      },
      {
        "id": 5,
        "question": "Which X760 engine should I avoid?",
        "answer": "We don't recommend outright avoidance, but a pre‑2019 2.0 Ingenium diesel without documented timing chain and balance shaft history is the one purchase we consistently advise against. The chain stretch risk is well documented, and a replacement can cost £4,500+ — a significant portion of the car's value."
      },
      {
        "id": 6,
        "question": "How do I know if my X760 engine needs replacing?",
        "answer": "Key warning signs: diesel — whine from the engine bay, rattle on cold start, or oil dilution symptoms; petrol — coolant loss with no external leak, overheating, or water pump noise; V6 — coolant loss, supercharger rattle at idle, or overheating. Use our diagnostic guide to identify the specific symptoms."
      },
      {
        "id": 7,
        "question": "Is it worth replacing a Jaguar XE X760 engine, or should I scrap the car?",
        "answer": "Apply our 60% Jaguar threshold. A £4,500 diesel recon against a £10,000 X760 is 45% — viable. Against a £6,000 example, the same recon is 75% — not worth it. For the V6, a £7,500 recon on a £12,000 car is 63% — borderline. Value the car first; if the repair exceeds 60%, walk away."
      },
      {
        "id": 8,
        "question": "How long do Jaguar XE X760 engines last?",
        "answer": "The 2.0 Ingenium petrol can exceed 150,000 miles with proper servicing. The diesel's limiting factor is the timing chain, which often shows issues between 60,000–120,000 miles — addressed proactively, it can last longer. The V6 is durable but needs cooling system attention every 60,000 miles."
      },
      {
        "id": 9,
        "question": "Is the X760 a single generation?",
        "answer": "Yes — the Jaguar XE was produced as a single generation from 2015 to 2024. There are no earlier or later XE generations. The X760 chassis code covers all XE saloons throughout this period. A 2019 facelift brought styling and interior updates but no major mechanical changes."
      },
      {
        "id": 10,
        "question": "How do I find my Jaguar XE X760 engine code?",
        "answer": "Listed on the VIN plate and vehicle documentation; block stamping varies by engine. For the 2.0 Ingenium, the code is on the block near the exhaust manifold. For the 3.0 V6, it's on the block face below the inlet manifold. Tell us your registration and we'll identify it for free."
      }
    ]
  },
  "trustCta": {
    "h2": "Why UK Jaguar XE X760 Owners Trust JaguarEngine.uk",
    "trustPoints": [
      {
        "title": "Trusted X760 Engine Suppliers",
        "text": "every garage and engine rebuilder in our network is vetted, rated and reviewed by real X760 owners, as part of the Engine Finders network."
      },
      {
        "title": "Compare Jaguar XE X760 Engine Replacement Companies",
        "text": "see prices, warranty terms and supply‑only vs supply‑fit options side‑by‑side before you commit."
      },
      {
        "title": "UK Engine Replacement Services for Jaguar XE X760",
        "text": "covering every variant from 20d to Project 8, with nationwide supply and specialist fitting available."
      }
    ],
    "finalCta": "Find the best Jaguar XE X760 engine replacement UK owners rely on. Compare real prices from trusted specialists on EnginesMarket today and get your X760 back on the road with confidence.",
    "ctaButton": {
      "label": "Compare Jaguar XE X760 Engine Prices on EnginesMarket →",
      "href": "#",
      "note": "[PLACEHOLDER — confirm EnginesMarket URL structure]"
    }
  }
}
