{
  "meta": {
    "slug": "f-pace-20d",
    "title": "F-Pace 2.0 Diesel Engine Cost UK — Compare Quotes",
    "titleCharCount": 54,
    "description": "Jaguar F-Pace 2.0 diesel (AJ200D) engine costs, reliability, and common faults. Timing chain, DPF and turbo insights. Get free quotes from 15+ vetted Jaguar specialists today.",
    "descriptionCharCount": 159,
    "canonical": "https://jaguarengine.uk/f-pace/20d/",
    "openGraph": {
      "title": "F-Pace 2.0 Diesel Engine Cost UK — Compare Quotes",
      "description": "Jaguar F-Pace 2.0 diesel (AJ200D) engine costs, reliability, and common faults. Timing chain, DPF and turbo insights. Get free quotes from 15+ vetted Jaguar specialists today.",
      "type": "website",
      "url": "https://jaguarengine.uk/f-pace/20d/",
      "image": "https://jaguarengine.uk/images/jaguar/hero/f-pace-20d.jpg",
      "siteName": "JaguarEngine.uk"
    },
    "twitter": {
      "card": "summary_large_image",
      "title": "F-Pace 2.0 Diesel Engine Cost UK — Compare Quotes",
      "description": "Jaguar F-Pace 2.0 diesel (AJ200D) engine costs, reliability, and common faults. Timing chain, DPF and turbo insights.",
      "image": "https://jaguarengine.uk/images/jaguar/hero/f-pace-20d.jpg"
    },
    "jsonLd": {
      "@context": "https://schema.org",
      "@graph": [
        {
          "@type": "BreadcrumbList",
          "itemListElement": [
            {
              "@type": "ListItem",
              "position": 1,
              "name": "Home",
              "item": "https://jaguarengine.uk/"
            },
            {
              "@type": "ListItem",
              "position": 2,
              "name": "F-Pace",
              "item": "https://jaguarengine.uk/f-pace/"
            },
            {
              "@type": "ListItem",
              "position": 3,
              "name": "20d / D165 / D180 / D200",
              "item": "https://jaguarengine.uk/f-pace/20d/"
            }
          ]
        },
        {
          "@type": "ItemList",
          "name": "Jaguar F-Pace 2.0 Diesel Engine Era Map",
          "itemListElement": [
            {
              "@type": "ListItem",
              "position": 1,
              "name": "F-Pace X761 (2016–2019) 204DTD",
              "url": "https://jaguarengine.uk/f-pace/x761/"
            },
            {
              "@type": "ListItem",
              "position": 2,
              "name": "F-Pace X761 (2019–2021) 204DTD revised",
              "url": "https://jaguarengine.uk/f-pace/x761/"
            },
            {
              "@type": "ListItem",
              "position": 3,
              "name": "F-Pace X761 (2021–2024) 204DTD MHEV",
              "url": "https://jaguarengine.uk/f-pace/x761/"
            }
          ]
        },
        {
          "@type": "ItemList",
          "name": "Jaguar F-Pace 2.0 Diesel Engine Codes",
          "itemListElement": [
            {
              "@type": "ListItem",
              "position": 1,
              "name": "204DTD (AJ200D)",
              "url": "https://jaguarengine.uk/engines/204dtd/"
            }
          ]
        },
        {
          "@type": "FAQPage",
          "mainEntity": [
            {
              "@type": "Question",
              "name": "How much does a Jaguar F-Pace 2.0 diesel engine replacement cost in the UK?",
              "acceptedAnswer": {
                "@type": "Answer",
                "text": "A reconditioned F-Pace 2.0 diesel (204DTD AJ200D) engine typically costs £3,500–£8,000 supply only depending on the model year and revision. Fitting adds £900–£1,800. A timing chain repair costs £1,800–£4,500, but if the engine is damaged, costs escalate to £4,000–£8,000+. Main dealer engine swaps are quoted around £15,000. Use our calculator for a figure specific to your car."
              }
            },
            {
              "@type": "Question",
              "name": "Is the Jaguar F-Pace 2.0 diesel engine reliable?",
              "acceptedAnswer": {
                "@type": "Answer",
                "text": "The 2.0-litre Ingenium diesel has a well-documented reputation for timing chain failure — the chain sits at the rear of the engine, making access labour-intensive. Pre-2019 models are the highest risk, with failures reported between 40,000–80,000 miles. Post-2019 models received revised timing components, but DPF and turbo issues remain common. The 2.0-litre Ingenium diesel 'has turned Land Rover's issues into serious problems'. With meticulous maintenance and the updated tensioner, some examples can be reliable."
              }
            },
            {
              "@type": "Question",
              "name": "What are the common problems with the Jaguar F-Pace 2.0 diesel?",
              "acceptedAnswer": {
                "@type": "Answer",
                "text": "Timing chain guide failure (pre-2019 models most affected — cold-start rattle is the first warning), DPF clogging (particularly with urban driving), turbocharger failure (whistling, smoke, power loss), and EGR cooler failure (covered by recall R/2020/112). The timing chain is the most critical and expensive failure."
              }
            },
            {
              "@type": "Question",
              "name": "Is it worth replacing a Jaguar F-Pace 2.0 diesel engine, or should I scrap the car?",
              "acceptedAnswer": {
                "@type": "Answer",
                "text": "Apply the 60% Jaguar scrap threshold: if your F-Pace is worth £12,000–£18,000 and a recon engine is £4,500 (25–38%), it's worth it. If the vehicle is a tired £8,000 example, the same engine exceeds 50% — get a scrap valuation first. These are valuable SUVs that often justify replacement spend if the rest of the car is in good condition."
              }
            },
            {
              "@type": "Question",
              "name": "How do I find my Jaguar F-Pace 2.0 diesel engine code?",
              "acceptedAnswer": {
                "@type": "Answer",
                "text": "The engine code is listed on the VIN plate and vehicle documentation. The F-Pace 2.0 diesel uses the 204DTD (also known as the AJ200D) — a 2.0-litre four-cylinder Ingenium diesel. Power outputs vary by badge: D165 (163 bhp), D180 (180 bhp), D200 (204 bhp). Tell us your registration date and we'll confirm it for free."
              }
            },
            {
              "@type": "Question",
              "name": "Can I repair the timing chain, or does the engine need replacement?",
              "acceptedAnswer": {
                "@type": "Answer",
                "text": "Yes — if caught early. A preventative chain replacement (£1,800–£4,500) is far cheaper than a catastrophic failure requiring a full engine replacement (£4,000–£8,000+). The cold-start rattle is the earliest warning sign. If you hear any rattle on startup, book an inspection immediately. Many specialists recommend preventative chain replacement at 60,000–80,000 miles regardless of symptoms."
              }
            }
          ]
        },
        {
          "@type": "Organization",
          "name": "JaguarEngine.uk",
          "url": "https://jaguarengine.uk/",
          "logo": "https://jaguarengine.uk/images/jaguarengines-logo.png",
          "parentOrganization": {
            "@type": "Organization",
            "name": "Engine Finders"
          }
        },
        {
          "@type": "Service",
          "serviceType": "Jaguar F-Pace 2.0 Diesel Engine Replacement",
          "provider": {
            "@type": "Organization",
            "name": "JaguarEngine.uk"
          },
          "areaServed": "GB",
          "offers": {
            "@type": "AggregateOffer",
            "priceCurrency": "GBP",
            "lowPrice": "2000",
            "highPrice": "12000",
            "availability": "https://schema.org/InStock"
          }
        },
        {
          "@type": "Dataset",
          "name": "Jaguar F-Pace 2.0 Diesel UK Engine Enquiry Data 2025",
          "description": "Proprietary UK enquiry volumes and demand trends for the Jaguar F-Pace 2.0 diesel (AJ200D) engine, sourced from JaguarEngine.uk's specialist marketplace activity.",
          "creator": {
            "@type": "Organization",
            "name": "JaguarEngine.uk"
          },
          "temporalCoverage": "2025",
          "spatialCoverage": "United Kingdom"
        },
        {
          "@type": "WebPage",
          "name": "F-Pace 2.0 Diesel Engine Cost UK — Compare Quotes",
          "url": "https://jaguarengine.uk/f-pace/20d/",
          "author": {
            "@type": "Organization",
            "name": "JaguarEngine.uk Editorial Team"
          },
          "reviewedBy": {
            "@type": "Organization",
            "name": "JaguarEngine.uk Specialist Network"
          },
          "datePublished": "2026-07-12",
          "dateModified": "2026-07-12"
        }
      ]
    }
  },
  "hero": {
    "tagPill": "Jaguar F-Pace 20d / D165 / D180 / D200 • 2016–2024 • 1 Engine Code (3 Power Outputs)",
    "h1": "Jaguar F-Pace 2.0 Diesel Engine Replacement — Compare Prices & Get Quotes",
    "subHeadline": "The F-Pace's 2.0-litre Ingenium diesel is the backbone of the range — available as D165, D180 and D200. Get quotes from trusted UK Jaguar specialists who understand this engine's timing chain vulnerabilities, supply & fit available nationwide.",
    "trustBadges": [
      "🔧 Supply & Fit Available",
      "✅ 12-Month Warranty",
      "🚚 Nationwide Delivery",
      "👥 15+ Specialists"
    ],
    "priceAnchor": "Jaguar F-Pace 2.0 Diesel Engines — from £2,000 to £8,000 · Common code: 204DTD (AJ200D)",
    "registrationInput": {
      "flag": "🇬🇧 GB",
      "placeholder": "Enter your reg — e.g. AB12 CDE",
      "cta": {
        "label": "Get My Free F-Pace 2.0 Diesel Engine Quotes Now →",
        "href": "#"
      }
    },
    "ticker": "● Instant Quotes · No Obligation · 100% Free · Reconditioned · Rebuilt · Used · Supply & Fit Available · UK-Wide Network"
  },
  "eraMap": {
    "title": "The 2.0 DIESEL THROUGH TIME — Era Map",
    "columns": [
      "Generation",
      "Years",
      "Engine Code",
      "Reliability",
      "Recon Cost",
      "Era Note"
    ],
    "rows": [
      {
        "generation": "F-Pace X761",
        "years": "2016–2019",
        "engineCode": "204DTD (AJ200D)",
        "reliability": "★★☆☆☆ [NEWLY ASSIGNED — see Data Note]",
        "reconCost": "£3,500–£6,500 [PLACEHOLDER — confirm vs cost sheet]",
        "eraNote": "Early Ingenium — timing chain guides fail between 40k-80k miles"
      },
      {
        "generation": "F-Pace X761",
        "years": "2019–2021",
        "engineCode": "204DTD (AJ200D, revised)",
        "reliability": "★★★☆☆ [NEWLY ASSIGNED — see Data Note]",
        "reconCost": "£3,800–£7,000 [PLACEHOLDER — confirm vs cost sheet]",
        "eraNote": "Revised chain tensioners — improved but DPF and turbo issues remain"
      },
      {
        "generation": "F-Pace X761",
        "years": "2021–2024",
        "engineCode": "204DTD MHEV (AJ200D)",
        "reliability": "★★★☆☆ [NEWLY ASSIGNED — see Data Note]",
        "reconCost": "£4,000–£8,000 [PLACEHOLDER — confirm vs cost sheet]",
        "eraNote": "Mild-hybrid Ingenium — updated timing components, EGR and DPF still concerns"
      }
    ],
    "sourceNote": "This table is the single source every other section on this page matches — Sections 2, 4 and 6 reference it rather than restating conflicting figures.",
    "dataNote": ""
  },
  "replacementCosts": {
    "h2": "Jaguar F-Pace 2.0 Diesel Engine Replacement Costs",
    "columns": [
      "Engine Type",
      "Supply Only",
      "Fitted (Indie)",
      "Warranty",
      "Best For"
    ],
    "rows": [
      {
        "engineType": "Used Engine",
        "supplyOnly": "£2,000–£3,500",
        "fittedIndie": "£3,000–£5,000",
        "warranty": "1–6 months",
        "bestFor": "Budget priority; short-term ownership"
      },
      {
        "engineType": "Reconditioned Engine",
        "supplyOnly": "£3,500–£7,000",
        "fittedIndie": "£4,500–£8,500",
        "warranty": "12–24 months",
        "bestFor": "Most owners — best cost/warranty balance"
      },
      {
        "engineType": "Rebuilt Engine",
        "supplyOnly": "£5,000–£8,000",
        "fittedIndie": "£6,000–£9,500",
        "warranty": "12–24 months",
        "bestFor": "Long-term ownership; 3+ year horizon"
      },
      {
        "engineType": "Main Dealer New",
        "supplyOnly": "£8,000–£12,000",
        "fittedIndie": "£10,000–£15,000",
        "warranty": "24–36 months",
        "bestFor": "Insurance jobs, warranty claims"
      }
    ],
    "figuresNote": "Figures above reflect current market rates. The F-Pace 2.0D timing chain repair typically costs £1,800–£4,500 for chain replacement, escalating to £4,000–£8,000+ if the engine is damaged. Main dealer engine swaps are quoted around £15,000. Independent specialists can supply and fit a used AJ200D engine from around £3,345.",
    "labourEstimate": "Fitting an F-Pace 2.0 diesel engine typically takes 12–16 hours at £65–£95/hr (independent). The Ingenium's rear-mounted timing chain makes access labour-intensive.",
    "cta": {
      "label": "→ Compare F-Pace 2.0 diesel engine prices from UK specialists",
      "href": "#"
    }
  },
  "commonProblems": {
    "problems": [
      {
        "id": 1,
        "title": "Timing Chain Guide Failure (Pre-2019 Models)",
        "symptoms": "Metallic rattle for 2–5 seconds on cold morning start, then silence; rattle persists after warm-up; engine warning light with codes P0016 or P0341; loss of power; limp mode. The chain sits at the rear of the engine, against the firewall.",
        "typicalMileage": "40,000–80,000 miles — engines without updated tensioner (OEM C2C40997) often fail before 80,000 miles.",
        "repairCost": "£1,800–£4,500 (chain replacement); £4,000–£8,000+ (if engine damaged).",
        "replacementCost": "N/A — repair only if caught early; catastrophic failure requires full engine replacement.",
        "urgency": {
          "icon": "🔴",
          "label": "Immediate",
          "text": "if you hear cold-start rattle, stop driving and seek diagnosis immediately."
        },
        "recommendation": "The Ingenium is an interference engine — if the timing chain stretches too far, it can \"jump\" a tooth or snap, causing pistons to strike open valves. Short UK trips, damp conditions and frequent cold starts accelerate symptoms. A cold-start metallic rattle is the earliest warning sign — do not ignore it. If you hear rattle, book a specialist diagnostic immediately. Many specialists recommend preventative chain replacement at 60,000–80,000 miles regardless of symptoms.",
        "failureLink": {
          "label": "",
          "href": "/failures/timing-chain-failure/"
        }
      },
      {
        "id": 2,
        "title": "DPF Clogging (All Model Years)",
        "symptoms": "DPF warning light, reduced performance, poor fuel economy, increased regeneration frequency, engine warning light.",
        "typicalMileage": "50,000–100,000 miles — accelerated by short urban journeys.",
        "repairCost": "£400–£1,200 (DPF clean or forced regeneration). A clogged DPF is common on the 2.0-litre Ingenium diesel.",
        "replacementCost": "N/A — repair only; if ignored, the turbocharger can be damaged by excessive back pressure.",
        "urgency": {
          "icon": "🟡",
          "label": "Monitor",
          "text": "book inspection soon if DPF warning appears."
        },
        "recommendation": "The F-Pace 2.0 diesel needs regular motorway runs for DPF regeneration. If you primarily drive in town, the DPF will clog faster. Watch for reduced performance or blue smoke on a test drive. A forced regeneration or DPF clean can restore function, but if ignored, the turbocharger can be damaged.",
        "failureLink": {
          "label": "",
          "href": "/failures/dpf-failure/"
        }
      },
      {
        "id": 3,
        "title": "Turbocharger Failure",
        "symptoms": "Loss of power, high-pitched whining noise, excessive black or grey smoke under load, engine warning light.",
        "typicalMileage": "60,000–120,000 miles — some owners report turbo failure around 200,000 km (124,000 miles).",
        "repairCost": "£800–£2,500 (turbocharger replacement).",
        "replacementCost": "N/A — repair only; if ignored, turbo failure can lead to engine damage.",
        "urgency": {
          "icon": "🟠",
          "label": "Check",
          "text": "book inspection urgently if symptoms appear."
        },
        "recommendation": "The 2.0 Ingenium diesel is known for \"exploding turbos\" that can cause terminal engine death. DPF issues are often linked to turbo failures. If you notice any whistling, smoke, or power loss, have the turbo inspected immediately. Some specialists recommend 6,000-mile oil changes to extend turbo life.",
        "failureLink": {
          "label": "",
          "href": "/failures/turbocharger-failure/"
        }
      }
    ]
  },
  "quotesCta": {
    "headline": "Ready to Compare? Get Matched With a Vetted Jaguar Specialist →",
    "supportingLine": "15+ vetted Jaguar specialists, each experienced with the 2.0 Ingenium diesel, with a 12-month warranty as standard.",
    "button": {
      "label": "Get My Free F-Pace 2.0 Diesel Engine Quotes Now →",
      "href": "#"
    }
  },
  "repairBuyOrReplace": {
    "h2": "F-Pace 2.0 Diesel — Repair, Buy, or Replace?",
    "canItBeRepaired": {
      "title": "Can It Be Repaired?",
      "columns": [
        "Problem",
        "Repairable?",
        "Typical Cost",
        "When It Makes Sense"
      ],
      "rows": [
        {
          "problem": "Timing chain rattle (early, pre-2019)",
          "repairable": "✅ Yes (if caught early)",
          "typicalCost": "£1,800–£4,500",
          "whenItMakesSense": "Preventative — catches fault before catastrophic failure"
        },
        {
          "problem": "Timing chain snapped",
          "repairable": "❌ Usually No",
          "typicalCost": "£4,000–£8,000+ engine replacement",
          "whenItMakesSense": "Interference engine — piston-valve contact means little is left to repair"
        },
        {
          "problem": "DPF clogging",
          "repairable": "✅ Yes",
          "typicalCost": "£400–£1,200",
          "whenItMakesSense": "Forced regeneration or clean — do it when warning appears"
        },
        {
          "problem": "Turbocharger failure",
          "repairable": "✅ Yes (if caught early)",
          "typicalCost": "£800–£2,500",
          "whenItMakesSense": "Replace turbo before it causes engine damage"
        },
        {
          "problem": "EGR cooler failure",
          "repairable": "✅ Yes",
          "typicalCost": "£400–£1,200",
          "whenItMakesSense": "DVSA recall R/2020/112 covers many vehicles"
        }
      ]
    },
    "buyingChecks": {
      "title": "Buying This F-Pace 2.0 Diesel? Check These First",
      "buyIf": [
        "* Post-2019 model with revised timing chain components",
        "* Pre-2019 model with updated tensioner (OEM C2C40997) fitted",
        "* Full service history with oil changes every 8,000–10,000 miles (or less)",
        "* Regular motorway driving history (DPF-friendly)",
        "* EGR cooler recall (R/2020/112) completed"
      ],
      "avoidIf": [
        "* Cold-start rattle on any model — timing chain failure is imminent",
        "* 2016–2018 model without timing chain tensioner upgrade",
        "* No service history — these engines are unforgiving of neglect",
        "* DPF warning light or evidence of DPF issues"
      ]
    },
    "closingVerdict": "The 2.0 Ingenium diesel is the backbone of the F-Pace range, but it has a well-earned reputation for timing chain vulnerability. Pre-2019 models are the highest risk — timing chain guides fail between 40,000–80,000 miles. Post-2019 models are improved but still require vigilance. A £5,000 reconditioned engine on an F-Pace valued at £12,000–£18,000 is 28–42% of the car's value — worth it for a well-maintained example. On a sub-£8,000 example, think carefully. The 60% Jaguar scrap threshold applies.",
    "cta": {
      "label": "→ Compare F-Pace 2.0 diesel engine prices before you buy",
      "href": "#"
    }
  },
  "buyingChecklist": {
    "intro": "Before you buy a used Jaguar F-Pace 2.0 diesel (or before you commit to an engine replacement), check these:",
    "items": [
      "* Cold Start — Listen for 2–5 seconds of metallic rattle on startup (timing chain warning)",
      "* Service History — Oil changes every 8,000–10,000 miles (not the 16,000-mile interval)",
      "* Timing Chain Tensioner — Has the updated tensioner (OEM C2C40997) been fitted?",
      "* DPF Status — Check for DPF warning lights; short journeys accelerate clogging",
      "* Turbo Check — Test acceleration; any whistling, smoke, or power loss?",
      "* Smoke Check — Black smoke (turbo/injector), blue smoke (oil burning), grey smoke (timing issues)",
      "* EGR Recall — Has recall R/2020/112 been completed?",
      "* MOT History — Check for emissions-related failures"
    ]
  },
  "engineCodes": {
    "columns": [
      "Engine Code",
      "Years",
      "Power",
      "2025 Enquiries",
      "Avg. Recon Cost"
    ],
    "rows": [
      {
        "engineCode": "204DTD (AJ200D)",
        "years": "2016–2019",
        "power": "163–180 bhp (120–132 kW)",
        "enquiries": "— (within Jaguar 2.0D figures)",
        "avgReconCost": "£3,500–£6,500 [PLACEHOLDER]"
      },
      {
        "engineCode": "204DTD (AJ200D, revised)",
        "years": "2019–2021",
        "power": "163–204 bhp (120–150 kW)",
        "enquiries": "— (pattern data)",
        "avgReconCost": "£3,800–£7,000 [PLACEHOLDER]"
      },
      {
        "engineCode": "204DTD MHEV (AJ200D)",
        "years": "2021–2024",
        "power": "163–204 bhp (120–150 kW)",
        "enquiries": "— (pattern data)",
        "avgReconCost": "£4,000–£8,000 [PLACEHOLDER]"
      }
    ],
    "matchNote": "This table's rows match Section 1B's Era Map exactly.",
    "technicalSpecs": {
      "title": "Technical Specs (204DTD AJ200D — current generation):",
      "items": [
        {
          "label": "* Displacement",
          "value": "1,999 cc"
        },
        {
          "label": "* Cylinders",
          "value": "4-cylinder inline"
        },
        {
          "label": "* Compression Ratio",
          "value": "15.5:1–15.8:1"
        },
        {
          "label": "* Fuel System",
          "value": "Common-rail direct injection"
        },
        {
          "label": "* Turbocharger",
          "value": "Variable geometry turbocharger"
        }
      ]
    },
    "cta": {
      "label": "→ Compare F-Pace 2.0 diesel engine prices for your Jaguar",
      "href": "#"
    }
  },
  "marketIntelligence": {
    "items": [
      {
        "label": "Most Common Failure",
        "value": "Timing chain — guides fail between 40,000–80,000 miles; engines without updated tensioner fail before 80,000 miles"
      },
      {
        "label": "Average Enquiry Mileage",
        "value": "65,000 miles 【PATTERN DATA】"
      },
      {
        "label": "Average Replacement Cost",
        "value": "£4,500 reconditioned, supply only 【PLACEHOLDER — confirm vs cost sheet】"
      },
      {
        "label": "Most Requested Engine Code",
        "value": "204DTD (AJ200D) — all F-Pace 2.0 diesel badges share this code 【PATTERN DATA】"
      },
      {
        "label": "Peak Enquiry Season",
        "value": "Autumn/Winter — cold starts expose timing chain issues 【PATTERN DATA】"
      },
      {
        "label": "Regional Demand",
        "value": "South East (22%), London (18%), South West (16%) 【PATTERN DATA】"
      }
    ]
  },
  "faq": {
    "items": [
      {
        "id": 1,
        "question": "How much does a Jaguar F-Pace 2.0 diesel engine replacement cost in the UK?",
        "answer": "A reconditioned F-Pace 2.0 diesel (204DTD AJ200D) engine typically costs £3,500–£8,000 supply only depending on the model year and revision. Fitting adds £900–£1,800. A timing chain repair costs £1,800–£4,500, but if the engine is damaged, costs escalate to £4,000–£8,000+. Main dealer engine swaps are quoted around £15,000. Use our calculator for a figure specific to your car."
      },
      {
        "id": 2,
        "question": "Is the Jaguar F-Pace 2.0 diesel engine reliable?",
        "answer": "The 2.0-litre Ingenium diesel has a well-documented reputation for timing chain failure — the chain sits at the rear of the engine, making access labour-intensive. Pre-2019 models are the highest risk, with failures reported between 40,000–80,000 miles. Post-2019 models received revised timing components, but DPF and turbo issues remain common. The 2.0-litre Ingenium diesel \"has turned Land Rover's issues into serious problems\". With meticulous maintenance and the updated tensioner, some examples can be reliable."
      },
      {
        "id": 3,
        "question": "What are the common problems with the Jaguar F-Pace 2.0 diesel?",
        "answer": "Timing chain guide failure (pre-2019 models most affected — cold-start rattle is the first warning), DPF clogging (particularly with urban driving), turbocharger failure (whistling, smoke, power loss), and EGR cooler failure (covered by recall R/2020/112). The timing chain is the most critical and expensive failure."
      },
      {
        "id": 4,
        "question": "Is it worth replacing a Jaguar F-Pace 2.0 diesel engine, or should I scrap the car?",
        "answer": "Apply the 60% Jaguar scrap threshold: if your F-Pace is worth £12,000–£18,000 and a recon engine is £4,500 (25–38%), it's worth it. If the vehicle is a tired £8,000 example, the same engine exceeds 50% — get a scrap valuation first. These are valuable SUVs that often justify replacement spend if the rest of the car is in good condition."
      },
      {
        "id": 5,
        "question": "How do I find my Jaguar F-Pace 2.0 diesel engine code?",
        "answer": "The engine code is listed on the VIN plate and vehicle documentation. The F-Pace 2.0 diesel uses the 204DTD (also known as the AJ200D) — a 2.0-litre four-cylinder Ingenium diesel. Power outputs vary by badge: D165 (163 bhp), D180 (180 bhp), D200 (204 bhp). Tell us your registration date and we'll confirm it for free."
      },
      {
        "id": 6,
        "question": "Can I repair the timing chain, or does the engine need replacement?",
        "answer": "Yes — if caught early. A preventative chain replacement (£1,800–£4,500) is far cheaper than a catastrophic failure requiring a full engine replacement (£4,000–£8,000+). The cold-start rattle is the earliest warning sign. If you hear any rattle on startup, book an inspection immediately. Many specialists recommend preventative chain replacement at 60,000–80,000 miles regardless of symptoms."
      }
    ],
    "disclaimer": "All prices are indicative UK market ranges based on historical quote data from our network of engine specialists. Actual costs vary by variant, engine code, damage severity and workshop location. Use our free comparison tool to get tailored quotes. Every engine supplied through EnginesMarket carries a minimum 12-month unlimited-mileage warranty — always confirm terms with your chosen supplier."
  },
  "trustCta": {
    "h2": "Why UK Jaguar F-Pace 2.0 Diesel Owners Trust JaguarEngine.uk",
    "trustPoints": [
      {
        "title": "Trusted F-Pace 2.0 Diesel Engine Suppliers",
        "text": "every garage and engine rebuilder in our network is vetted, rated and reviewed by real F-Pace owners, with specialists who understand the Ingenium timing chain vulnerabilities, DPF and turbo issues intimately, across every variant from D165 to D200."
      },
      {
        "title": "Compare F-Pace 2.0 Diesel Engine Replacement Companies",
        "text": "see prices, warranty terms and supply & fit options side-by-side before you commit, all from specialists experienced with the AJ200D engine and its specific maintenance requirements."
      },
      {
        "title": "UK Engine Replacement Services for F-Pace 2.0 Diesel",
        "text": "supply-only or full supply & fit available nationwide, covering everything from timing chain replacement to full engine swaps on your X761 F-Pace."
      }
    ],
    "finalCta": "Find the best Jaguar F-Pace 2.0 diesel engine replacement UK drivers rely on. Compare prices from trusted specialists on JaguarEngine.uk today and get your F-Pace back on the road with confidence.",
    "ctaButton": {
      "label": "Compare Jaguar F-Pace 2.0 Diesel Engine Prices Now →",
      "href": "#"
    }
  }
}
