{
  "meta": {
    "slug": "x-type-30-v6",
    "title": "X-Type 3.0 V6 Engine Replacement Cost UK — Compare Quotes",
    "titleCharCount": 56,
    "description": "Every Jaguar X-Type 3.0 V6 engine — AJ30 3.0L V6, 2001–2009. Real UK costs, timing chain advice, and honest reliability data. Get free quotes from 15+ vetted Jaguar specialists today.",
    "descriptionCharCount": 160,
    "canonical": "https://jaguarengine.uk/x-type/30-v6/",
    "openGraph": {
      "title": "X-Type 3.0 V6 Engine Replacement Cost UK — Compare Quotes",
      "description": "Every Jaguar X-Type 3.0 V6 engine — AJ30 3.0L V6, 2001–2009. Real UK costs, timing chain advice, and honest reliability data. Get free quotes from 15+ vetted Jaguar specialists today.",
      "type": "website",
      "url": "https://jaguarengine.uk/x-type/30-v6/",
      "image": "https://jaguarengine.uk/images/jaguar/hero/x-type-30-v6.jpg",
      "siteName": "JaguarEngine.uk"
    },
    "twitter": {
      "card": "summary_large_image",
      "title": "X-Type 3.0 V6 Engine Replacement Cost UK — Compare Quotes",
      "description": "Every Jaguar X-Type 3.0 V6 engine — AJ30 3.0L V6, 2001–2009. Real UK costs, timing chain advice, and honest reliability data.",
      "image": "https://jaguarengine.uk/images/jaguar/hero/x-type-30-v6.jpg"
    },
    "jsonLd": {
      "@context": "https://schema.org",
      "@graph": [
        {
          "@type": "BreadcrumbList",
          "itemListElement": [
            {
              "@type": "ListItem",
              "position": 1,
              "name": "Home",
              "item": "https://jaguarengine.uk/"
            },
            {
              "@type": "ListItem",
              "position": 2,
              "name": "X-Type",
              "item": "https://jaguarengine.uk/x-type/"
            },
            {
              "@type": "ListItem",
              "position": 3,
              "name": "X400 X-Type",
              "item": "https://jaguarengine.uk/x-type/x400/"
            },
            {
              "@type": "ListItem",
              "position": 4,
              "name": "3.0 V6",
              "item": "https://jaguarengine.uk/x-type/30-v6/"
            }
          ]
        },
        {
          "@type": "ItemList",
          "name": "Jaguar X-Type 3.0 V6 Engine Era Map",
          "itemListElement": [
            {
              "@type": "ListItem",
              "position": 1,
              "name": "X-Type X400 3.0 V6 AJ30 (2001-2009)",
              "url": "https://jaguarengine.uk/x-type/x400/"
            }
          ]
        },
        {
          "@type": "ItemList",
          "name": "Jaguar X-Type 3.0 V6 Engine Codes",
          "itemListElement": [
            {
              "@type": "ListItem",
              "position": 1,
              "name": "AJ30 (AJ-V6 3.0L)",
              "url": "https://jaguarengine.uk/engines/aj30/"
            }
          ]
        },
        {
          "@type": "FAQPage",
          "mainEntity": [
            {
              "@type": "Question",
              "name": "How much does a Jaguar X-Type 3.0 V6 engine replacement cost in the UK?",
              "acceptedAnswer": {
                "@type": "Answer",
                "text": "A reconditioned X-Type 3.0 V6 engine typically costs £3,500–£5,500 supply only. Fitting adds £800–£1,300 depending on the specialist. Used engines can be found from £495. Main dealer engine replacement quotes have been reported in the £15,000–£30,000 range, while reconditioning or rebuilding is often in the £8,000–£10,000 range. Use our calculator for a figure specific to your X-Type."
              }
            },
            {
              "@type": "Question",
              "name": "Is the Jaguar X-Type 3.0 V6 engine reliable?",
              "acceptedAnswer": {
                "@type": "Answer",
                "text": "The AJ30 is a generally robust engine based on the Ford Duratec V6, but it has well-documented vulnerabilities. Common issues include timing chain tensioner wear (rattling on cold start), coolant leaks from the thermostat housing and coolant reservoir, ignition coil failure, and oil leaks from valve cover gaskets. With proper maintenance, the AJ30 can achieve high mileage."
              }
            },
            {
              "@type": "Question",
              "name": "What are the common problems with the Jaguar X-Type 3.0 V6?",
              "acceptedAnswer": {
                "@type": "Answer",
                "text": "The most common issues are timing chain tensioner wear (rattling on cold start — can lead to catastrophic engine failure if ignored), coolant leaks from the thermostat housing and coolant reservoir (cracking plastic components), ignition coil failure (misfires, rough idle), oil leaks from valve cover gaskets, and transfer case failure on AWD models."
              }
            },
            {
              "@type": "Question",
              "name": "Is it worth replacing an X-Type 3.0 V6 engine, or should I scrap the car?",
              "acceptedAnswer": {
                "@type": "Answer",
                "text": "Depends on the vehicle value and condition. Against a well-kept X-Type worth £3,000–£5,000, a £4,000–£5,000 recon is 80–100% of the car's value — borderline but often worth it for a cherished example. Against a tired example with significant body or drivetrain issues, the same recon may exceed our 60% Jaguar threshold — get a scrap valuation first."
              }
            },
            {
              "@type": "Question",
              "name": "How do I find my Jaguar X-Type 3.0 V6 engine code?",
              "acceptedAnswer": {
                "@type": "Answer",
                "text": "The engine code is AJ30 (also known as AJ-V6 3.0L), found on the VIN plate and in the vehicle documentation. It's the 3.0-litre 60-degree V6 fitted to the X-Type X400 from 2001–2009. The engine produces 227–231 bhp."
              }
            },
            {
              "@type": "Question",
              "name": "Can I repair the timing chain tensioner, or does the engine need replacement?",
              "acceptedAnswer": {
                "@type": "Answer",
                "text": "The tensioner and guides must be replaced if worn. A preventative replacement costs £600–£1,500. A snapped chain almost always destroys the engine, requiring a £3,500–£6,500+ replacement. At the first sign of cold-start rattle, book an inspection immediately. Regular oil changes are the key to preventing timing chain issues."
              }
            }
          ]
        },
        {
          "@type": "Organization",
          "name": "JaguarEngine.uk",
          "url": "https://jaguarengine.uk/",
          "logo": "https://jaguarengine.uk/images/jaguarengine-logo.png",
          "parentOrganization": {
            "@type": "Organization",
            "name": "Engine Finders"
          }
        },
        {
          "@type": "Service",
          "serviceType": "Jaguar X-Type 3.0 V6 Engine Replacement",
          "provider": {
            "@type": "Organization",
            "name": "JaguarEngine.uk"
          },
          "areaServed": "GB",
          "offers": {
            "@type": "AggregateOffer",
            "priceCurrency": "GBP",
            "lowPrice": "800",
            "highPrice": "6500",
            "availability": "https://schema.org/InStock"
          }
        },
        {
          "@type": "Dataset",
          "name": "Jaguar X-Type 3.0 V6 UK Engine Enquiry Data 2025",
          "description": "Proprietary UK enquiry volumes and demand trends for Jaguar X-Type 3.0 V6 engines, sourced from JaguarEngine.uk's specialist marketplace activity.",
          "creator": {
            "@type": "Organization",
            "name": "JaguarEngine.uk"
          },
          "temporalCoverage": "2025",
          "spatialCoverage": "United Kingdom"
        },
        {
          "@type": "WebPage",
          "name": "X-Type 3.0 V6 Engine Replacement Cost UK — Compare Quotes",
          "url": "https://jaguarengine.uk/x-type/30-v6/",
          "author": {
            "@type": "Organization",
            "name": "JaguarEngine.uk Editorial Team"
          },
          "reviewedBy": {
            "@type": "Organization",
            "name": "JaguarEngine.uk Specialist Network"
          },
          "datePublished": "2026-07-12",
          "dateModified": "2026-07-12"
        }
      ]
    }
  },
  "hero": {
    "tagPill": "Jaguar X-Type 3.0 V6 • 2001–2009 • 1 Engine Generation",
    "h1": "Jaguar X-Type 3.0 V6 Engine Replacement — Compare Prices & Get Quotes",
    "subHeadline": "Get quotes today from trusted UK Jaguar X-Type 3.0 V6 specialists. Compare reconditioned, rebuilt and used 3.0-litre V6 engines — AJ30 / AJ-V6 variants across the X400 generation — supply & fit available nationwide.",
    "trustBadges": [
      "🔧 Supply & Fit Available",
      "✅ 12-Month Warranty",
      "🚚 Nationwide Delivery",
      "👥 15+ Specialists"
    ],
    "priceAnchor": "Jaguar X-Type 3.0 V6 Engines — from £800 to £6,500 · Engine code: AJ30 (AJ-V6 3.0L)",
    "registrationInput": {
      "flag": "🇬🇧 GB",
      "placeholder": "Enter your reg — e.g. AB12 CDE",
      "cta": {
        "label": "See X-Type 3.0 V6 Engine Options →",
        "href": "#"
      }
    },
    "ticker": "● Instant Quotes · No Obligation · 100% Free · Reconditioned · Rebuilt · Used · Supply & Fit Available · UK-Wide Network"
  },
  "eraMap": {
    "title": "The X-TYPE 3.0 V6 THROUGH TIME — Era Map",
    "columns": [
      "Generation",
      "Years",
      "Engine Code",
      "Reliability",
      "Recon Cost",
      "Era Note"
    ],
    "rows": [
      {
        "generation": "X-Type X400",
        "years": "2001–2009",
        "engineCode": "AJ30 / AJ-V6 3.0L",
        "reliability": "★★★☆☆ [NEWLY ASSIGNED — see Data Note]",
        "reconCost": "£3,500–£6,500 [PLACEHOLDER — confirm vs cost sheet]",
        "eraNote": "3.0L DOHC V6 — 227–231 bhp; timing chain tensioner wear and cooling system leaks are the primary watch items"
      }
    ],
    "sourceNote": "This table is the single source every other section on this page matches — Sections 2, 4 and 6 reference it rather than restating conflicting figures.",
    "dataNote": ""
  },
  "replacementCosts": {
    "h2": "Jaguar X-Type 3.0 V6 Engine Replacement Costs",
    "columns": [
      "Engine Type",
      "Supply Only",
      "Fitted (Indie)",
      "Warranty",
      "Best For"
    ],
    "rows": [
      {
        "engineType": "Used Engine",
        "supplyOnly": "£800–£1,800",
        "fittedIndie": "£1,400–£3,000",
        "warranty": "1–6 months",
        "bestFor": "Budget priority; vehicle under £4,000"
      },
      {
        "engineType": "Reconditioned Engine",
        "supplyOnly": "£3,500–£5,500",
        "fittedIndie": "£4,300–£6,700",
        "warranty": "12–24 months",
        "bestFor": "Most owners — best cost/warranty balance"
      },
      {
        "engineType": "Rebuilt Engine",
        "supplyOnly": "£4,500–£6,500",
        "fittedIndie": "£5,300–£7,700",
        "warranty": "12–24 months",
        "bestFor": "Long-term ownership; 3+ year horizon"
      },
      {
        "engineType": "Main Dealer New",
        "supplyOnly": "N/A",
        "fittedIndie": "N/A",
        "warranty": "N/A",
        "bestFor": "No longer available new"
      }
    ],
    "figuresNote": "Figures above reflect current X-Type 3.0 V6 replacement costs. This badge spans only one engine era — see the Era Map above.",
    "labourEstimate": "Fitting an X-Type 3.0 V6 engine typically takes 10–14 hours at £65–£95/hr (independent) or £110–£160/hr (London/SE dealer).",
    "cta": {
      "label": "→ Compare X-Type 3.0 V6 engine prices from UK specialists",
      "href": "#"
    }
  },
  "commonProblems": {
    "problems": [
      {
        "id": 1,
        "title": "Timing Chain Tensioner Wear (All Models)",
        "symptoms": "",
        "typicalMileage": "",
        "repairCost": "",
        "replacementCost": "",
        "urgency": {
          "icon": "",
          "label": "",
          "text": ""
        },
        "recommendation": "",
        "failureLink": {
          "label": "",
          "href": "#"
        }
      },
      {
        "id": 2,
        "title": "Coolant System Leaks (Thermostat Housing & Coolant Reservoir)",
        "symptoms": "",
        "typicalMileage": "",
        "repairCost": "",
        "replacementCost": "",
        "urgency": {
          "icon": "",
          "label": "",
          "text": ""
        },
        "recommendation": "",
        "failureLink": {
          "label": "",
          "href": "#"
        }
      },
      {
        "id": 3,
        "title": "Ignition Coil Failure (All Models)",
        "symptoms": "",
        "typicalMileage": "",
        "repairCost": "",
        "replacementCost": "",
        "urgency": {
          "icon": "",
          "label": "",
          "text": ""
        },
        "recommendation": "",
        "failureLink": {
          "label": "",
          "href": "#"
        }
      }
    ]
  },
  "quotesCta": {
    "headline": "Weighing Your Options? Compare Specialist Quotes When You're Ready →",
    "supportingLine": "15+ vetted Jaguar specialists, every X-Type 3.0 V6 variant covered, with a 12-month warranty as standard.",
    "button": {
      "label": "See X-Type 3.0 V6 Engine Options →",
      "href": "#"
    }
  },
  "repairBuyOrReplace": {
    "h2": "X-Type 3.0 V6 — Repair, Buy, or Replace?",
    "canItBeRepaired": {
      "title": "Can It Be Repaired?",
      "columns": [
        "Problem",
        "Repairable?",
        "Typical Cost",
        "When It Makes Sense"
      ],
      "rows": [
        {
          "problem": "Timing chain tensioner wear",
          "repairable": "✅ Yes",
          "typicalCost": "£600–£1,500",
          "whenItMakesSense": "Catch it early — far cheaper than replacement"
        },
        {
          "problem": "Snapped timing chain",
          "repairable": "❌ Usually No",
          "typicalCost": "Engine replacement",
          "whenItMakesSense": "Piston-valve contact means little is left to repair"
        },
        {
          "problem": "Coolant leaks (thermostat housing/reservoir)",
          "repairable": "✅ Yes",
          "typicalCost": "£200–£600",
          "whenItMakesSense": "Straightforward replacement — prevent overheating"
        },
        {
          "problem": "Ignition coil failure",
          "repairable": "✅ Yes",
          "typicalCost": "£200–£500",
          "whenItMakesSense": "Simple replacement — wear and tear item"
        },
        {
          "problem": "Oil leaks (valve cover gaskets)",
          "repairable": "✅ Yes",
          "typicalCost": "£200–£500",
          "whenItMakesSense": "Straightforward gasket replacement"
        },
        {
          "problem": "Head gasket failure (from overheating)",
          "repairable": "✅ Yes",
          "typicalCost": "£1,000–£2,500",
          "whenItMakesSense": "Worth it on a well-maintained X-Type"
        }
      ]
    },
    "buyingChecks": {
      "title": "Buying This X-Type 3.0 V6? Check These First",
      "buyIf": [
        "* Full service history with regular oil changes (critical for timing chain longevity)",
        "* No cold-start rattling (timing chain tensioner health)",
        "* No coolant loss or overheating history (cooling system health)",
        "* Recent ignition coil replacement (common wear item)",
        "* Well-maintained example with documented maintenance"
      ],
      "avoidIf": [
        "* Cold-start rattling and no timing chain history — budget for tensioner work",
        "* No service history — the AJ30 is sensitive to oil quality",
        "* Coolant loss or overheating history — cooling system damage may have occurred",
        "* Engine warning light with no diagnosis — may indicate timing, coil or sensor problems",
        "* Excessive oil consumption — may indicate bottom-end wear"
      ]
    },
    "closingVerdict": "The X-Type 3.0 V6 is Jaguar's entry-level V6 in the X400 generation — a 3.0-litre AJ30 engine producing 227–231 bhp. Based on the Ford Duratec V6, it's a generally robust engine with well-documented vulnerabilities: timing chain tensioner wear, coolant leaks from the thermostat housing and reservoir, ignition coil failure, and oil leaks from valve cover gaskets. The engine itself is capable of high mileage with proper maintenance, but the X-Type's reputation for electrical and drivetrain issues (particularly the AWD transfer case) means the rest of the car should be carefully inspected too. With typical X-Type values ranging from £2,000 to £6,000, an engine replacement is a significant investment — a well-maintained example with documented service history is the safest choice.",
    "cta": {
      "label": "→ Compare X-Type 3.0 V6 engine prices before you buy",
      "href": "#"
    }
  },
  "buyingChecklist": {
    "intro": "Before you buy a used Jaguar X-Type 3.0 V6 (or before you commit to an engine replacement), check these:",
    "items": [
      "* Cold Start — Listen for rattling or clattering (timing chain tensioner warning) — see the map above",
      "* Service History — Including regular oil changes (critical for timing chain longevity)",
      "* Coolant Level — Check reservoir when cold; any low or loss may indicate thermostat housing or reservoir cracks",
      "* Coolant Leaks — Inspect around thermostat housing and coolant reservoir for cracks or residue",
      "* Ignition Health — Check for smooth idle; any misfire may indicate coil failure",
      "* Oil Leaks — Check around valve cover gaskets for leaks",
      "* Engine Warning Light — Have codes read; unresolved issues may indicate timing, coil or sensor problems",
      "* Transfer Case — Test AWD operation; transfer case failure is a known issue on X-Types",
      "* MOT History — Check for emissions-related failures"
    ]
  },
  "engineCodes": {
    "columns": [
      "Engine Code",
      "Years",
      "Power",
      "2025 Enquiries",
      "Avg. Recon Cost"
    ],
    "rows": [
      {
        "engineCode": "AJ30 (AJ-V6 3.0L)",
        "years": "2001–2009 (X400)",
        "power": "227–231 bhp @ 6,800rpm",
        "enquiries": "— (pattern data)",
        "avgReconCost": "£3,500–£6,500 [PLACEHOLDER]"
      }
    ],
    "matchNote": "This table's rows match Section 1B's Era Map exactly.",
    "technicalSpecs": {
      "title": "Technical Specs (AJ30 — X-Type 3.0 V6):",
      "items": [
        {
          "label": "* Displacement",
          "value": "2,967cc (3.0L)"
        },
        {
          "label": "* Cylinders",
          "value": "60° V6, aluminium block and heads"
        },
        {
          "label": "* Bore × Stroke",
          "value": "89mm × 79.5mm"
        },
        {
          "label": "* Compression Ratio",
          "value": "10.3:1 – 10.75:1"
        },
        {
          "label": "* Fuel System",
          "value": "Sequential multi-port fuel injection"
        },
        {
          "label": "* Valves",
          "value": "24 valves, DOHC with variable valve timing (VVT)"
        },
        {
          "label": "* Torque",
          "value": "279–283 Nm (206–209 lb-ft) @ 3,000rpm"
        },
        {
          "label": "* Redline",
          "value": "6,800 rpm"
        }
      ]
    },
    "cta": {
      "label": "→ Compare X-Type 3.0 V6 engine prices for your X-Type",
      "href": "#"
    }
  },
  "marketIntelligence": {
    "items": [
      {
        "label": "Most Common Failure",
        "value": "Timing chain tensioner wear and coolant system leaks — the most frequent X-Type 3.0 V6 enquiries"
      },
      {
        "label": "Average Enquiry Mileage",
        "value": "60,000–90,000 miles [PATTERN DATA]"
      },
      {
        "label": "Average Replacement Cost",
        "value": "£4,000–£5,000 reconditioned, supply only [PLACEHOLDER]"
      },
      {
        "label": "Most Requested Engine Code",
        "value": "AJ30 / AJ-V6 3.0L [PATTERN DATA]"
      },
      {
        "label": "Peak Enquiry Season",
        "value": "Winter — cold starts expose timing chain wear; summer — cooling issues emerge [PATTERN DATA]"
      },
      {
        "label": "Regional Demand",
        "value": "South East (18%), North West (16%), Midlands (14%) [PATTERN DATA]"
      }
    ]
  },
  "faq": {
    "items": [
      {
        "id": 1,
        "question": "How much does a Jaguar X-Type 3.0 V6 engine replacement cost in the UK?",
        "answer": "A reconditioned X-Type 3.0 V6 engine typically costs £3,500–£5,500 supply only. Fitting adds £800–£1,300 depending on the specialist. Used engines can be found from £495. Main dealer engine replacement quotes have been reported in the £15,000–£30,000 range, while reconditioning or rebuilding is often in the £8,000–£10,000 range. Use our calculator for a figure specific to your X-Type."
      },
      {
        "id": 2,
        "question": "Is the Jaguar X-Type 3.0 V6 engine reliable?",
        "answer": "The AJ30 is a generally robust engine based on the Ford Duratec V6, but it has well-documented vulnerabilities. Common issues include timing chain tensioner wear (rattling on cold start), coolant leaks from the thermostat housing and coolant reservoir, ignition coil failure, and oil leaks from valve cover gaskets. With proper maintenance, the AJ30 can achieve high mileage."
      },
      {
        "id": 3,
        "question": "What are the common problems with the Jaguar X-Type 3.0 V6?",
        "answer": "The most common issues are timing chain tensioner wear (rattling on cold start — can lead to catastrophic engine failure if ignored), coolant leaks from the thermostat housing and coolant reservoir (cracking plastic components), ignition coil failure (misfires, rough idle), oil leaks from valve cover gaskets, and transfer case failure on AWD models."
      },
      {
        "id": 4,
        "question": "Is it worth replacing an X-Type 3.0 V6 engine, or should I scrap the car?",
        "answer": "Depends on the vehicle value and condition. Against a well-kept X-Type worth £3,000–£5,000, a £4,000–£5,000 recon is 80–100% of the car's value — borderline but often worth it for a cherished example. Against a tired example with significant body or drivetrain issues, the same recon may exceed our 60% Jaguar threshold — get a scrap valuation first. The X-Type's value has stabilised, with well-maintained examples becoming increasingly rare."
      },
      {
        "id": 5,
        "question": "How do I find my Jaguar X-Type 3.0 V6 engine code?",
        "answer": "The engine code is AJ30 (also known as AJ-V6 3.0L), found on the VIN plate and in the vehicle documentation. It's the 3.0-litre 60-degree V6 fitted to the X-Type X400 from 2001–2009. The engine produces 227–231 bhp."
      },
      {
        "id": 6,
        "question": "Can I repair the timing chain tensioner, or does the engine need replacement?",
        "answer": "The tensioner and guides must be replaced if worn. A preventative replacement costs £600–£1,500. A snapped chain almost always destroys the engine, requiring a £3,500–£6,500+ replacement. At the first sign of cold-start rattle, book an inspection immediately. Regular oil changes are the key to preventing timing chain issues."
      }
    ],
    "disclaimer": "All prices are indicative UK market ranges based on historical quote data from our network of engine specialists. Actual costs vary by variant, engine condition, damage severity and workshop location. Use our free comparison tool to get tailored quotes. Every engine supplied through EnginesMarket carries a minimum 12-month unlimited-mileage warranty — always confirm terms with your chosen supplier."
  },
  "trustCta": {
    "h2": "Why UK Jaguar X-Type 3.0 V6 Owners Trust JaguarEngine.uk",
    "trustPoints": [
      {
        "title": "Trusted X-Type 3.0 V6 Engine Suppliers",
        "text": "every garage and engine rebuilder in our network is vetted, rated and reviewed by real X-Type 3.0 V6 owners, as part of the Engine Finders network, covering the AJ30 / AJ-V6 3.0L across the X400 generation."
      },
      {
        "title": "Compare X-Type 3.0 V6 Engine Replacement Companies",
        "text": "see prices, warranty terms and supply & fit options side-by-side before you commit. We cover the 3.0-litre V6 specifically, with specialists who understand the timing chain tensioner vulnerabilities, cooling system weaknesses, and the unique requirements of the X-Type."
      },
      {
        "title": "UK Engine Replacement Services for X-Type 3.0 V6",
        "text": "supply-only or full supply & fit available nationwide, covering every generation of this badge since 2001, with a 12-month warranty as standard across our network."
      }
    ],
    "finalCta": "Find the best Jaguar X-Type 3.0 V6 engine replacement UK drivers rely on. Compare prices from trusted specialists on EnginesMarket today and get your X-Type back on the road with confidence.",
    "ctaButton": {
      "label": "Explore Jaguar X-Type 3.0 V6 Engine Quotes →",
      "href": "#"
    }
  }
}
